housing_market_sim/__init__.py
housing_market_sim/app.py
housing_market_sim/assets/home_icon.png
housing_market_sim/assets/key_icon.png
housing_market_sim/assets/llm_icon.png
housing_market_sim/assets/visualization_icon.png
housing_market_sim-0.1.7.dist-info/METADATA
housing_market_sim-0.1.7.dist-info/WHEEL
housing_market_sim-0.1.7.dist-info/entry_points.txt
housing_market_sim-0.1.7.dist-info/top_level.txt
housing_market_sim-0.1.7.dist-info/RECORD
