Metadata-Version: 2.4
Name: housing_market_sim
Version: 0.1.7
Summary: 基于ABM的住房过滤动态仿真模拟系统
Home-page: https://github.com/yourusername/housing_market_sim
Author: ZhangZuo LiuXiaoge
Author-email: lxg5880@163.com
License: MIT
Classifier: Programming Language :: Python :: 3
Classifier: License :: OSI Approved :: MIT License
Classifier: Operating System :: OS Independent
Classifier: Intended Audience :: Developers
Classifier: Topic :: Software Development :: Libraries :: Application Frameworks
Requires-Python: >=3.8
Requires-Dist: streamlit>=1.25.0
Requires-Dist: matplotlib>=3.7.0
Requires-Dist: numpy>=1.23.0
Requires-Dist: mesa<2.2,>=1.2.1
Requires-Dist: openai>=1.3.5
Requires-Dist: pandas>=1.5.3
Requires-Dist: scipy>=1.10.0
Requires-Dist: requests>=2.31.0
Requires-Dist: tqdm>=4.64.1
Dynamic: author
Dynamic: author-email
Dynamic: classifier
Dynamic: description
Dynamic: description-content-type
Dynamic: home-page
Dynamic: license
Dynamic: requires-dist
Dynamic: requires-python
Dynamic: summary
